django_http_compression/__init__.py
django_http_compression/apps.py
django_http_compression/middleware.py
django_http_compression/py.typed
django_http_compression-1.1.0.dist-info/licenses/LICENSE
django_http_compression-1.1.0.dist-info/METADATA
django_http_compression-1.1.0.dist-info/WHEEL
django_http_compression-1.1.0.dist-info/top_level.txt
django_http_compression-1.1.0.dist-info/RECORD
