Metadata-Version: 2.4
Name: django-http-compression
Version: 1.1.0
Summary: Django middleware for compressing HTTP responses with Zstandard, Brotli, or Gzip.
Author-email: Adam Johnson <me@adamj.eu>
License-Expression: MIT
Project-URL: Changelog, https://github.com/adamchainz/django-http-compression/blob/main/CHANGELOG.rst
Project-URL: Funding, https://adamj.eu/books/
Project-URL: Repository, https://github.com/adamchainz/django-http-compression
Keywords: Django
Classifier: Development Status :: 5 - Production/Stable
Classifier: Framework :: Django :: 4.2
Classifier: Framework :: Django :: 5.0
Classifier: Framework :: Django :: 5.1
Classifier: Framework :: Django :: 5.2
Classifier: Framework :: Django :: 6.0
Classifier: Intended Audience :: Developers
Classifier: Natural Language :: English
Classifier: Operating System :: OS Independent
Classifier: Programming Language :: Python :: 3 :: Only
Classifier: Programming Language :: Python :: 3.9
Classifier: Programming Language :: Python :: 3.10
Classifier: Programming Language :: Python :: 3.11
Classifier: Programming Language :: Python :: 3.12
Classifier: Programming Language :: Python :: 3.13
Classifier: Programming Language :: Python :: 3.14
Classifier: Programming Language :: Python :: Implementation :: CPython
Classifier: Typing :: Typed
Requires-Python: >=3.9
License-File: LICENSE
Requires-Dist: asgiref>=3.6
Requires-Dist: backports-zstd>=1; python_version < "3.14"
Requires-Dist: django>=4.2
Requires-Dist: typing-extensions>=4.1
Provides-Extra: brotli
Requires-Dist: brotli>=1.0.1; extra == "brotli"
Dynamic: license-file
